five.localsitemanager-4.0-py3.11-nspkg.pth
five/localsitemanager/__init__.py
five/localsitemanager/browser.py
five/localsitemanager/browser.txt
five/localsitemanager/components.pt
five/localsitemanager/configure.zcml
five/localsitemanager/localsitemanager.txt
five/localsitemanager/overrides.zcml
five/localsitemanager/registry.py
five/localsitemanager/tests.py
five/localsitemanager/utils.py
five.localsitemanager-4.0.dist-info/LICENSE.rst
five.localsitemanager-4.0.dist-info/METADATA
five.localsitemanager-4.0.dist-info/WHEEL
five.localsitemanager-4.0.dist-info/namespace_packages.txt
five.localsitemanager-4.0.dist-info/top_level.txt
five.localsitemanager-4.0.dist-info/RECORD
