Metadata-Version: 2.1
Name: five.localsitemanager
Version: 4.0
Summary: Local site manager implementation for Zope.
Home-page: https://github.com/zopefoundation/five.localsitemanager
Author: Zope Foundation and Contributors
Author-email: zope-dev@zope.dev
License: ZPL 2.1
Project-URL: Issue Tracker, https://github.com/zopefoundation/five.localsitemanager/issues
Project-URL: Sources, https://github.com/zopefoundation/five.localsitemanager
Keywords: zope five sitemanager
Classifier: Development Status :: 5 - Production/Stable
Classifier: Environment :: Web Environment
Classifier: Framework :: Zope :: 5
Classifier: License :: OSI Approved :: Zope Public License
Classifier: Operating System :: OS Independent
Classifier: Programming Language :: Python
Classifier: Programming Language :: Python :: 3
Classifier: Programming Language :: Python :: 3.7
Classifier: Programming Language :: Python :: 3.8
Classifier: Programming Language :: Python :: 3.9
Classifier: Programming Language :: Python :: 3.10
Classifier: Programming Language :: Python :: 3.11
Classifier: Programming Language :: Python :: Implementation :: CPython
Classifier: Topic :: Internet :: WWW/HTTP :: Site Management
Requires-Python: >=3.7
License-File: LICENSE.rst
Requires-Dist: Acquisition
Requires-Dist: persistent
Requires-Dist: setuptools
Requires-Dist: zope.component
Requires-Dist: zope.event
Requires-Dist: zope.interface (>=3.8)
Requires-Dist: zope.location
Requires-Dist: zope.lifecycleevent
Requires-Dist: zope.site
Requires-Dist: zope.testing
Requires-Dist: Zope (>=4.0b1)
